LICENSE.txt
MANIFEST.in
README.rst
setup.cfg
setup.py
wopmars/Base.py
wopmars/DAG.py
wopmars/Observable.py
wopmars/Parser.py
wopmars/Reader.py
wopmars/SQLManager.py
wopmars/ToolWrapperObserver.py
wopmars/ToolWrapperThread.py
wopmars/WopmarsQuery.py
wopmars/WopmarsSession.py
wopmars/WorkflowManager.py
wopmars/__init__.py
wopmars.egg-info/PKG-INFO
wopmars.egg-info/SOURCES.txt
wopmars.egg-info/dependency_links.txt
wopmars.egg-info/entry_points.txt
wopmars.egg-info/requires.txt
wopmars.egg-info/top_level.txt
wopmars/data/example/Wopfile.yml
wopmars/data/example/Wopfile2.yml
wopmars/data/example/Wopfile3.yml
wopmars/data/example/__init__.py
wopmars/data/example/bats.sh
wopmars/data/example/setup.py
wopmars/data/example/example.egg-info/PKG-INFO
wopmars/data/example/example.egg-info/SOURCES.txt
wopmars/data/example/example.egg-info/dependency_links.txt
wopmars/data/example/example.egg-info/top_level.txt
wopmars/data/example/input/pieces.txt
wopmars/data/example/model/DatedPiece.py
wopmars/data/example/model/Piece.py
wopmars/data/example/model/PieceCar.py
wopmars/data/example/model/__init__.py
wopmars/data/example/output/empty.txt
wopmars/data/example/wrapper/AddDateToPiece.py
wopmars/data/example/wrapper/CarAssembler.py
wopmars/data/example/wrapper/SparePartsManufacturer.py
wopmars/data/example/wrapper/__init__.py
wopmars/models/Execution.py
wopmars/models/FileInputOutputInformation.py
wopmars/models/InputOutput.py
wopmars/models/Option.py
wopmars/models/TableInputOutputInformation.py
wopmars/models/TableModificationTime.py
wopmars/models/ToolWrapper.py
wopmars/models/TypeInputOrOutput.py
wopmars/models/__init__.py
wopmars/tests/__init__.py
wopmars/tests/test_cmd_example.py
wopmars/tests/test_dag.py
wopmars/tests/test_example.py
wopmars/tests/test_file_input_output_information.py
wopmars/tests/test_option.py
wopmars/tests/test_parser.py
wopmars/tests/test_reader.py
wopmars/tests/test_sql_manager.py
wopmars/tests/test_table_input_output_information.py
wopmars/tests/test_tool_wrapper.py
wopmars/tests/test_tool_wrapper_thread.py
wopmars/tests/test_wopmars.py
wopmars/tests/test_wopmars_session.py
wopmars/tests/test_workflow_manager.py
wopmars/tests/resource/__init__.py
wopmars/tests/resource/input_files/__init__.py
wopmars/tests/resource/model/BaseWrongClassName.py
wopmars/tests/resource/model/FooBase.py
wopmars/tests/resource/model/FooBase2.py
