Metadata-Version: 2.1
Name: wopmars
Version: 0.1.5
Summary: Workflow Python Manager for Reproducible Science
Home-page: https://github.com/aitgon/wopmars
Download-URL: https://github.com/aitgon/wopmars/archive/0.1.5.tar.gz
Author: Aitor Gonzalez, Luc Giffon, Lionel Spinelli
Author-email: aitor.gonzalez@univ-amu.fr
License: MIT
Keywords: workflow manager python object-oriented reproducible science database framework
Classifier: Development Status :: 4 - Beta
Classifier: Environment :: Console
Classifier: Intended Audience :: Developers
Classifier: Intended Audience :: Science/Research
Classifier: License :: OSI Approved :: MIT License
Classifier: Programming Language :: Python
Classifier: Programming Language :: Python :: 3
Classifier: Programming Language :: Python :: 3.6
Classifier: Programming Language :: Python :: 3.7
Classifier: Programming Language :: Python :: 3.8
Classifier: Programming Language :: Python :: 3.9
Classifier: Programming Language :: Python :: 3.10
Classifier: Programming Language :: Python :: 3 :: Only
Classifier: Topic :: Database :: Front-Ends
Classifier: Topic :: Scientific/Engineering :: Bio-Informatics
Classifier: Topic :: Scientific/Engineering :: Information Analysis
Classifier: Topic :: Software Development
Classifier: Operating System :: POSIX :: Linux
Classifier: Operating System :: Microsoft :: Windows :: Windows 10
Provides-Extra: pygraphviz
License-File: LICENSE.txt
